fixerbaba/__init__.py
fixerbaba-1.0.dist-info/LICENSE
fixerbaba-1.0.dist-info/METADATA
fixerbaba-1.0.dist-info/WHEEL
fixerbaba-1.0.dist-info/entry_points.txt
fixerbaba-1.0.dist-info/top_level.txt
fixerbaba-1.0.dist-info/RECORD
