Metadata-Version: 2.1
Name: fixerbaba
Version: 1.0
Summary: Simple Tool For Fix B2K4 Error
Home-page: https://github.com/BotolMehedi/b2k4
Author: BotolMehedi
Author-email: Botol@email.com
License: UNKNOWN
Platform: UNKNOWN
Classifier: Programming Language :: Python :: 2
Classifier: License :: OSI Approved :: MIT License
Classifier: Operating System :: OS Independent
Requires-Python: >=2.7
